litebee/__about__.py
litebee/__init__.py
litebee/commands.py
litebee/core.py
litebee/utils.py
litebee-0.8.3.dist-info/METADATA
litebee-0.8.3.dist-info/WHEEL
litebee-0.8.3.dist-info/licenses/LICENSE
litebee-0.8.3.dist-info/RECORD
