Metadata-Version: 2.4
Name: litebee
Version: 0.8.3
Summary: A Python3 module to compile LiteBee Client Case files.
Project-URL: Documentation, https://github.com/K-R-Lucas/PyBeeClient#readme
Project-URL: Issues, https://github.com/K-R-Lucas/PyBeeClient/issues
Project-URL: Source, https://github.com/K-R-Lucas/PyBeeClient
Author-email: K-R-Lucas <kadenrlucas@yahoo.com.au>
License-Expression: GPL-3.0
License-File: LICENSE
Classifier: Development Status :: 4 - Beta
Classifier: Programming Language :: Python
Classifier: Programming Language :: Python :: 3.10
Classifier: Programming Language :: Python :: 3.11
Classifier: Programming Language :: Python :: 3.12
Classifier: Programming Language :: Python :: 3.13
Classifier: Programming Language :: Python :: Implementation :: CPython
Requires-Python: >=3.10
Requires-Dist: pygame-ce>=2.5.6
